[
  {
    "id": "c64d5f20-33bf-49a7-9355-d833eac99be2",
    "fullName": "Santos Bruen",
    "avatar": "https://avatars.githubusercontent.com/u/46733758",
    "email": "Michele70@hotmail.com",
    "streetAddress": "13551 Hirthe Summit",
    "city": "East Mathiasboro",
    "country": "Chad",
    "zipCode": "38160"
  },
  {
    "id": "1af4fa64-4daf-4d28-85a4-0d61432f8d6c",
    "fullName": "Johnathan Borer PhD",
    "avatar": "https://cloudflare-ipfs.com/ipfs/Qmd3W5DuhgHirLHGVixi6V76LhCkZUz6pnFt5AJBiyvHye/avatar/449.jpg",
    "email": "Bennett93@hotmail.com",
    "streetAddress": "148 Sharon Wall",
    "city": "Fort Reggieburgh",
    "country": "Palau",
    "zipCode": "91911-4970"
  },
  {
    "id": "dbebc7c7-f6fb-4447-b9eb-72fd9d309441",
    "fullName": "Roberta Hamill",
    "avatar": "https://cloudflare-ipfs.com/ipfs/Qmd3W5DuhgHirLHGVixi6V76LhCkZUz6pnFt5AJBiyvHye/avatar/272.jpg",
    "email": "Noble67@hotmail.com",
    "streetAddress": "70581 Brycen Crossing",
    "city": "San Diego",
    "country": "Wallis and Futuna",
    "zipCode": "11132"
  },
  {
    "id": "d6b5f4a1-b4ca-4cf5-b738-f9bd36491767",
    "fullName": "Angel Barton",
    "avatar": "https://cloudflare-ipfs.com/ipfs/Qmd3W5DuhgHirLHGVixi6V76LhCkZUz6pnFt5AJBiyvHye/avatar/1088.jpg",
    "email": "Kenneth.Dietrich@gmail.com",
    "streetAddress": "802 Langworth Streets",
    "city": "Southfield",
    "country": "Guinea",
    "zipCode": "10996-6299"
  },
  {
    "id": "50ba6e2e-2c4b-423a-a9b2-2d64c2b0a948",
    "fullName": "Fannie Keebler",
    "avatar": "https://avatars.githubusercontent.com/u/194657",
    "email": "Nayeli_Runte@hotmail.com",
    "streetAddress": "30151 Itzel Track",
    "city": "North Nona",
    "country": "Bosnia and Herzegovina",
    "zipCode": "80309-9232"
  },
  {
    "id": "c7bc8756-de3a-43a4-b14a-2dc3be98e401",
    "fullName": "Dr. Oliver Barton",
    "avatar": "https://cloudflare-ipfs.com/ipfs/Qmd3W5DuhgHirLHGVixi6V76LhCkZUz6pnFt5AJBiyvHye/avatar/707.jpg",
    "email": "Della66@yahoo.com",
    "streetAddress": "8033 Tad Locks",
    "city": "Starkworth",
    "country": "Taiwan",
    "zipCode": "54532"
  },
  {
    "id": "f5221e4e-1d32-413b-b833-b4ca9941d034",
    "fullName": "Natalie Harber",
    "avatar": "https://cloudflare-ipfs.com/ipfs/Qmd3W5DuhgHirLHGVixi6V76LhCkZUz6pnFt5AJBiyvHye/avatar/106.jpg",
    "email": "Edward_Lebsack@gmail.com",
    "streetAddress": "9352 E 5th Street",
    "city": "Binsstad",
    "country": "Malaysia",
    "zipCode": "04354-9807"
  },
  {
    "id": "66be8b2b-1852-44ca-8dd8-3ecc1767c7aa",
    "fullName": "Ada Rath",
    "avatar": "https://cloudflare-ipfs.com/ipfs/Qmd3W5DuhgHirLHGVixi6V76LhCkZUz6pnFt5AJBiyvHye/avatar/1222.jpg",
    "email": "Clint_Schowalter79@hotmail.com",
    "streetAddress": "53520 Adams Street",
    "city": "Kunzeburgh",
    "country": "Argentina",
    "zipCode": "53874-7276"
  },
  {
    "id": "9561a0f1-85b9-47b7-af95-0c5f312c6062",
    "fullName": "Lana Herzog",
    "avatar": "https://avatars.githubusercontent.com/u/24125701",
    "email": "Maryse80@hotmail.com",
    "streetAddress": "90098 Kuhlman Creek",
    "city": "South Julien",
    "country": "Egypt",
    "zipCode": "10210"
  },
  {
    "id": "97bc051f-891d-4c2b-884e-ff8d9877646f",
    "fullName": "Calvin Leannon",
    "avatar": "https://avatars.githubusercontent.com/u/3533685",
    "email": "Reece_Russel@yahoo.com",
    "streetAddress": "44811 Main Avenue",
    "city": "Enolashire",
    "country": "Cambodia",
    "zipCode": "57146-0931"
  },
  {
    "id": "0b833b94-e9f8-47ad-b896-8940ea83467c",
    "fullName": "Gerard Hessel",
    "avatar": "https://avatars.githubusercontent.com/u/64108177",
    "email": "Beau81@hotmail.com",
    "streetAddress": "119 Jeff Curve",
    "city": "Port Amayahaven",
    "country": "Oman",
    "zipCode": "31982-9040"
  },
  {
    "id": "781da4d9-0707-4267-bf0a-3eef8cd4988a",
    "fullName": "Ella Huels",
    "avatar": "https://avatars.githubusercontent.com/u/44177887",
    "email": "Sigurd_Weimann@yahoo.com",
    "streetAddress": "93412 Shemar Port",
    "city": "East Eleanorashire",
    "country": "Switzerland",
    "zipCode": "98757-9417"
  },
  {
    "id": "5b68de72-9f9c-4787-ad60-20764cdb3d4c",
    "fullName": "Willie Macejkovic",
    "avatar": "https://cloudflare-ipfs.com/ipfs/Qmd3W5DuhgHirLHGVixi6V76LhCkZUz6pnFt5AJBiyvHye/avatar/429.jpg",
    "email": "Boris.Leffler1@gmail.com",
    "streetAddress": "23507 Kuhlman Manor",
    "city": "Emelieview",
    "country": "Turkmenistan",
    "zipCode": "10300"
  },
  {
    "id": "7ece489b-ff16-46b2-a69f-7a1ff0ce0dea",
    "fullName": "Jerald Feest",
    "avatar": "https://avatars.githubusercontent.com/u/86876548",
    "email": "Manley27@gmail.com",
    "streetAddress": "727 Marshall Port",
    "city": "Keanutown",
    "country": "Palestine",
    "zipCode": "89342-8379"
  },
  {
    "id": "f14a20e8-0d94-4fd6-91cd-85a438af7425",
    "fullName": "Rex Fritsch",
    "avatar": "https://cloudflare-ipfs.com/ipfs/Qmd3W5DuhgHirLHGVixi6V76LhCkZUz6pnFt5AJBiyvHye/avatar/894.jpg",
    "email": "Paolo68@hotmail.com",
    "streetAddress": "99479 Olson Walks",
    "city": "Brookline",
    "country": "Republic of Korea",
    "zipCode": "73441-4927"
  },
  {
    "id": "9b09e7b6-26d0-420a-9f3c-3f254459d9b1",
    "fullName": "Wesley Walter",
    "avatar": "https://cloudflare-ipfs.com/ipfs/Qmd3W5DuhgHirLHGVixi6V76LhCkZUz6pnFt5AJBiyvHye/avatar/905.jpg",
    "email": "Mohammed.Rogahn50@gmail.com",
    "streetAddress": "708 Hortense Cove",
    "city": "South Cornell",
    "country": "Costa Rica",
    "zipCode": "31856-5472"
  },
  {
    "id": "7a9f468a-99be-4435-970f-d0f105c63e12",
    "fullName": "Emanuel Hauck",
    "avatar": "https://cloudflare-ipfs.com/ipfs/Qmd3W5DuhgHirLHGVixi6V76LhCkZUz6pnFt5AJBiyvHye/avatar/646.jpg",
    "email": "Rosario6@hotmail.com",
    "streetAddress": "45855 Bahringer Prairie",
    "city": "West Abigayleville",
    "country": "Thailand",
    "zipCode": "12902"
  },
  {
    "id": "f15f5810-8c1d-42aa-bb6a-c99bd5ab6e2e",
    "fullName": "Darren Gusikowski",
    "avatar": "https://avatars.githubusercontent.com/u/95160949",
    "email": "Amely.OReilly55@hotmail.com",
    "streetAddress": "862 E River Road",
    "city": "Torpborough",
    "country": "Virgin Islands, U.S.",
    "zipCode": "21274"
  },
  {
    "id": "9bacc3a5-e838-4ed1-badd-f7b8e33f6ec7",
    "fullName": "Candice Rolfson II",
    "avatar": "https://cloudflare-ipfs.com/ipfs/Qmd3W5DuhgHirLHGVixi6V76LhCkZUz6pnFt5AJBiyvHye/avatar/431.jpg",
    "email": "Otto.Ferry@yahoo.com",
    "streetAddress": "27305 Bridgette Valley",
    "city": "Schimmelstead",
    "country": "Barbados",
    "zipCode": "58842-2104"
  },
  {
    "id": "9b896b17-89de-482e-897c-e0f4d95e3d14",
    "fullName": "Duane Kerluke",
    "avatar": "https://avatars.githubusercontent.com/u/21027721",
    "email": "Burnice95@yahoo.com",
    "streetAddress": "15974 Lacy Route",
    "city": "East Lorenzo",
    "country": "Benin",
    "zipCode": "51309"
  }
]
